[{"content":"Hello whoever is reading this! This is my first post on my blog ever. Perhaps no one will ever read these posts, but that\u0026rsquo;s fine! I\u0026rsquo;m writing these to have a nice public journal of my efforts in game and software development.\nI won\u0026rsquo;t announce what I\u0026rsquo;m making yet, but I\u0026rsquo;m getting started. I have 1 game and 1 piece of software I\u0026rsquo;m planning to develop over the coming months.\nI really don\u0026rsquo;t have much to say here. I plan to focus this blog on my development and not on myself, so I don\u0026rsquo;t really want to give some big introduction.\nI hope one day you\u0026rsquo;re reading this blog and eagerly awaiting my next post because you\u0026rsquo;re so excited for my game or software to come out. I\u0026rsquo;ve created this blog with the hope that one day someone gets to experience that joy that I\u0026rsquo;ve felt before.\nThanks for reading!\nHere\u0026rsquo;s a wreath I drew last year.\n","permalink":"https://toyking10.net/posts/1/1/","summary":"Hello whoever is reading this! This is my first post on my blog ever. Perhaps no one will ever read these posts, but that\u0026rsquo;s fine! I\u0026rsquo;m writing these to have a nice public journal of my efforts in game and software development.\nI won\u0026rsquo;t announce what I\u0026rsquo;m making yet, but I\u0026rsquo;m getting started. I have 1 game and 1 piece of software I\u0026rsquo;m planning to develop over the coming months.","title":"My Goals"},{"content":"I make games. Currently, I haven\u0026rsquo;t released any. Stay tuned for future updates.\n","permalink":"https://toyking10.net/games/","summary":"I make games. Currently, I haven\u0026rsquo;t released any. Stay tuned for future updates.","title":""},{"content":"I make software. Currently, I haven\u0026rsquo;t released any. Stay tuned for future updates.\n","permalink":"https://toyking10.net/software/","summary":"I make software. Currently, I haven\u0026rsquo;t released any. Stay tuned for future updates.","title":""}]